LICENSE
README.md
dash_material_components/Alert.py
dash_material_components/Autocomplete.py
dash_material_components/Box.py
dash_material_components/Button.py
dash_material_components/Calendar.py
dash_material_components/CodeEditor.py
dash_material_components/Dashboard.py
dash_material_components/Dropdown.py
dash_material_components/IconButton.py
dash_material_components/InputText.py
dash_material_components/NavBar.py
dash_material_components/Page.py
dash_material_components/Section.py
dash_material_components/SideBar.py
dash_material_components/Slider.py
dash_material_components/Tab.py
dash_material_components/Table.py
dash_material_components/Toggle.py
dash_material_components/Typography.py
dash_material_components/__init__.py
dash_material_components/_imports_.py
dash_material_components/async-calendar.js
dash_material_components/async-calendar.js.map
dash_material_components/async-codeeditor.js
dash_material_components/async-codeeditor.js.map
dash_material_components/dash_material_components.js
dash_material_components/dash_material_components.js.map
dash_material_components/metadata.json
dash_material_components/package-info.json
dash_material_components/themes/__init__.py
dash_material_components/themes/base.py
dash_material_components/themes/plotly.py
dash_material_components/themes/static/logo.png
dash_material_components/themes/utils.py
package.json
dash_material_components-2.1.0.dist-info/LICENSE
dash_material_components-2.1.0.dist-info/METADATA
dash_material_components-2.1.0.dist-info/WHEEL
dash_material_components-2.1.0.dist-info/RECORD
