Metadata-Version: 2.1
Name: dash-material-components
Version: 2.1.0
Summary: Dash Material Design components for the Noos platform.
Home-page: https://github.com/noosenergy/dash-material-components
License: MIT
Author: Noos Energy
Author-email: contact@noos.energy
Requires-Python: >=3.12,<4.0
Classifier: Development Status :: 3 - Alpha
Classifier: Intended Audience :: Developers
Classifier: License :: OSI Approved :: MIT License
Classifier: Operating System :: OS Independent
Classifier: Programming Language :: Python :: 3
Classifier: Programming Language :: Python :: 3.12
Classifier: Typing :: Typed
Requires-Dist: dash (>=2.10,<3.0)
